auxiliary/__init__.py
auxiliary/file_explorer.py
auxiliary/message_keys.py
i2pdf-1.1.1.data/scripts/main_app.py
i2pdf-1.1.1.dist-info/LICENSE
i2pdf-1.1.1.dist-info/METADATA
i2pdf-1.1.1.dist-info/WHEEL
i2pdf-1.1.1.dist-info/entry_points.txt
i2pdf-1.1.1.dist-info/top_level.txt
i2pdf-1.1.1.dist-info/RECORD
