Metadata-Version: 2.1
Name: i2pdf
Version: 1.1.1
Summary: A simple CLI app that combines images to a single .pdf
Home-page: https://github.com/christopher-chandler
Author: Christopher Michael Chandler
Author-email: christopher.chandler@outlook.de
License: MIT
Platform: UNKNOWN
License-File: LICENSE
Requires-Dist: typer
Requires-Dist: PyYAML
Requires-Dist: Pillow
Requires-Dist: PyPDF2
